py_script_exec/__init__.py
py_script_exec/runner.py
py_script_exec/utils.py
tests/__init__.py
tests/test_runner.py
py_script_exec-1.2.0.dist-info/LICENSE
py_script_exec-1.2.0.dist-info/METADATA
py_script_exec-1.2.0.dist-info/WHEEL
py_script_exec-1.2.0.dist-info/top_level.txt
py_script_exec-1.2.0.dist-info/RECORD
