Metadata-Version: 2.1
Name: py_script_exec
Version: 1.2.0
Summary: A cross-platform Python script runner.
Home-page: https://github.com/jon429r/py_script_exec
Author: jon429r
Author-email: jonathanday088@gmail.com
Classifier: Programming Language :: Python :: 3
Classifier: License :: OSI Approved :: MIT License
Classifier: Operating System :: OS Independent
Requires-Python: >=3.6
License-File: LICENSE
